fret_ibra-0.2.0.dist-info/DESCRIPTION.rst
fret_ibra-0.2.0.dist-info/METADATA
fret_ibra-0.2.0.dist-info/RECORD
fret_ibra-0.2.0.dist-info/WHEEL
fret_ibra-0.2.0.dist-info/entry_points.txt
fret_ibra-0.2.0.dist-info/metadata.json
fret_ibra-0.2.0.dist-info/top_level.txt
fret_ibra-0.2.0.dist-info/zip-safe
ibra/__init__.py
ibra/__main__.py
ibra/background_subtraction.py
ibra/functions.py
ibra/ibra.py
ibra/ratiometric_processing.py
