Metadata-Version: 2.0
Name: fret-ibra
Version: 0.2.0
Summary: FRET-IBRA is used to process fluorescence resonance energy transfer (FRET) intensity data to produce ratiometric images for further analysis
Home-page: https://github.com/gmunglani/fret-ibra
Author: Gautam Munglani
Author-email: gmunglani@gmail.com
License: BSD
Keywords: opencv,background subtraction,DBSCAN clustering,FRET imaging,ratiometric
Platform: UNKNOWN
Requires-Python: >=2.7
Requires-Dist: configparser
Requires-Dist: h5py
Requires-Dist: imreg-dft
Requires-Dist: matplotlib
Requires-Dist: numpy
Requires-Dist: opencv-python
Requires-Dist: pims
Requires-Dist: scikit-image
Requires-Dist: scikit-learn
Requires-Dist: scipy
